gym_minigrid/__init__.py
gym_minigrid/benchmark.py
gym_minigrid/manual_control.py
gym_minigrid/minigrid.py
gym_minigrid/rendering.py
gym_minigrid/roomgrid.py
gym_minigrid/window.py
gym_minigrid/wrappers.py
gym_minigrid/envs/__init__.py
gym_minigrid/envs/blockedunlockpickup.py
gym_minigrid/envs/crossing.py
gym_minigrid/envs/distshift.py
gym_minigrid/envs/doorkey.py
gym_minigrid/envs/dynamicobstacles.py
gym_minigrid/envs/empty.py
gym_minigrid/envs/fetch.py
gym_minigrid/envs/fourrooms.py
gym_minigrid/envs/gotodoor.py
gym_minigrid/envs/gotoobject.py
gym_minigrid/envs/keycorridor.py
gym_minigrid/envs/lavagap.py
gym_minigrid/envs/lockedroom.py
gym_minigrid/envs/memory.py
gym_minigrid/envs/multiroom.py
gym_minigrid/envs/obstructedmaze.py
gym_minigrid/envs/playground.py
gym_minigrid/envs/putnear.py
gym_minigrid/envs/redbluedoors.py
gym_minigrid/envs/unlock.py
gym_minigrid/envs/unlockpickup.py
gym_minigrid-1.2.2.dist-info/LICENSE
gym_minigrid-1.2.2.dist-info/METADATA
gym_minigrid-1.2.2.dist-info/WHEEL
gym_minigrid-1.2.2.dist-info/entry_points.txt
gym_minigrid-1.2.2.dist-info/top_level.txt
gym_minigrid-1.2.2.dist-info/RECORD
