Metadata-Version: 2.1
Name: gym-minigrid
Version: 1.2.2
Summary: Minimalistic gridworld reinforcement learning environments
Home-page: https://github.com/Farama-Foundation/gym-minigrid
Author: Farama Foundation
Author-email: jkterry@farama.org
License: Apache
Keywords: memory,environment,agent,rl,gym
Classifier: Development Status :: 5 - Production/Stable
Classifier: Programming Language :: Python :: 3
Classifier: Programming Language :: Python :: 3.7
Classifier: Programming Language :: Python :: 3.8
Classifier: Programming Language :: Python :: 3.9
Classifier: Programming Language :: Python :: 3.10
Requires-Python: >=3.7
Provides-Extra: testing
License-File: LICENSE
